urljsf/__init__.py
urljsf/_schema.py
urljsf/cli.py
urljsf/config.py
urljsf/constants.py
urljsf/errors.py
urljsf/py.typed
urljsf/schema.py
urljsf/source.py
urljsf/urljsf.py
urljsf/utils.py
urljsf/_static/urljsf/246.616b0de5.js
urljsf/_static/urljsf/246.616b0de5.js.LICENSE.txt
urljsf/_static/urljsf/246.616b0de5.js.map
urljsf/_static/urljsf/405.b804e999.js
urljsf/_static/urljsf/405.b804e999.js.LICENSE.txt
urljsf/_static/urljsf/405.b804e999.js.map
urljsf/_static/urljsf/668.26206c82.js
urljsf/_static/urljsf/668.26206c82.js.LICENSE.txt
urljsf/_static/urljsf/668.26206c82.js.map
urljsf/_static/urljsf/674.48e1ebba.js
urljsf/_static/urljsf/674.48e1ebba.js.LICENSE.txt
urljsf/_static/urljsf/674.48e1ebba.js.map
urljsf/_static/urljsf/864.18f08627.js
urljsf/_static/urljsf/864.18f08627.js.LICENSE.txt
urljsf/_static/urljsf/864.18f08627.js.map
urljsf/_static/urljsf/87.113f7a94.js
urljsf/_static/urljsf/87.113f7a94.js.LICENSE.txt
urljsf/_static/urljsf/87.113f7a94.js.map
urljsf/_static/urljsf/947.65d01490.js
urljsf/_static/urljsf/947.65d01490.js.LICENSE.txt
urljsf/_static/urljsf/947.65d01490.js.map
urljsf/_static/urljsf/996.921bfb44.js
urljsf/_static/urljsf/996.921bfb44.js.LICENSE.txt
urljsf/_static/urljsf/bootstrap.min.css
urljsf/_static/urljsf/index.js
urljsf/_static/urljsf/index.js.LICENSE.txt
urljsf/_static/urljsf/index.js.map
urljsf/_static/urljsf/third-party-licenses.json
urljsf/_static/urljsf/demo/index.html
urljsf/_static/urljsf/demo/json/file.data.json
urljsf/_static/urljsf/demo/json/file.schema.json
urljsf/_static/urljsf/demo/json/file.uischema.json
urljsf/_static/urljsf/demo/json/url.schema.json
urljsf/_static/urljsf/demo/json/url.uischema.json
urljsf/_static/urljsf/demo/json/urljsf.json
urljsf/_static/urljsf/demo/toml/file.data.toml
urljsf/_static/urljsf/demo/toml/file.schema.toml
urljsf/_static/urljsf/demo/toml/file.uischema.toml
urljsf/_static/urljsf/demo/toml/url.schema.toml
urljsf/_static/urljsf/demo/toml/url.uischema.toml
urljsf/_static/urljsf/demo/toml/urljsf.toml
urljsf-0.1.5.dist-info/entry_points.txt
urljsf-0.1.5.dist-info/LICENSE
urljsf-0.1.5.dist-info/WHEEL
urljsf-0.1.5.dist-info/METADATA
urljsf-0.1.5.dist-info/RECORD
