Metadata-Version: 2.3
Name: urljsf
Version: 0.1.5
Summary: Build declarative, interactive HTML forms with JSON Schema
Author: urljsf contributors
Requires-Python: >=3.9
Classifier: Framework :: Sphinx :: Extension
Classifier: Framework :: Sphinx
Classifier: License :: OSI Approved :: BSD License
Classifier: Programming Language :: Python :: 3 :: Only
Classifier: Programming Language :: Python :: 3
Classifier: Topic :: File Formats :: JSON :: JSON Schema
Classifier: Topic :: File Formats :: JSON
Classifier: Topic :: File Formats
Classifier: Typing :: Typed
Requires-Dist: jinja2
Requires-Dist: jsonschema[format] >=4.18
Requires-Dist: tomli; python_version < '3.11'
Requires-Dist: typing_extensions >=4.0.0; python_version < '3.11'
Requires-Dist: mkdocs >=1.5 ; extra == "mkdocs"
Requires-Dist: pymdown-extensions >=10.11.0 ; extra == "mkdocs"
Requires-Dist: sphinx >=6.1 ; extra == "sphinx"
Requires-Dist: pytest ; extra == "test"
Requires-Dist: pytest-console-scripts ; extra == "test"
Requires-Dist: tomli-w ; extra == "test"
Requires-Dist: ruamel.yaml ; extra == "yaml"
Project-URL: Bug Tracker, https://github.com/deathbeds/urljsf/issues
Project-URL: Changelog, https://github.com/deathbeds/urljsf/blob/main/CHANGELOG.md
Project-URL: Documentation, https://urljsf.rtfd.org
Project-URL: PyPI, https://pypi.org/project/urljsf
Project-URL: Source, https://github.com/deathbeds/urljsf
Provides-Extra: mkdocs
Provides-Extra: sphinx
Provides-Extra: test
Provides-Extra: yaml
